skill_free_music_archive/LICENSE.md
skill_free_music_archive/README.md
skill_free_music_archive/__init__.py
skill_free_music_archive/skill.json
skill_free_music_archive/version.py
skill_free_music_archive/locale/en-us/articles.voc
skill_free_music_archive/locale/en-us/genre.voc
skill_free_music_archive/locale/uk-ua/articles.voc
skill_free_music_archive/locale/uk-ua/genre.voc
skill_free_music_archive/neon_skill_free_music_archive.egg-info/PKG-INFO
skill_free_music_archive/neon_skill_free_music_archive.egg-info/SOURCES.txt
skill_free_music_archive/neon_skill_free_music_archive.egg-info/dependency_links.txt
skill_free_music_archive/neon_skill_free_music_archive.egg-info/entry_points.txt
skill_free_music_archive/neon_skill_free_music_archive.egg-info/requires.txt
skill_free_music_archive/neon_skill_free_music_archive.egg-info/top_level.txt
skill_free_music_archive/test/test_skill.py
neon_skill_free_music_archive-1.1.0.dist-info/LICENSE.md
neon_skill_free_music_archive-1.1.0.dist-info/METADATA
neon_skill_free_music_archive-1.1.0.dist-info/WHEEL
neon_skill_free_music_archive-1.1.0.dist-info/entry_points.txt
neon_skill_free_music_archive-1.1.0.dist-info/top_level.txt
neon_skill_free_music_archive-1.1.0.dist-info/RECORD
