Metadata-Version: 2.1
Name: neon-skill-free-music-archive
Version: 1.1.0
Home-page: https://github.com/NeonGeckoCom/skill-free_music_archive
Author: Neongecko
Author-email: developers@neon.ai
License: BSD-3-Clause
License-File: LICENSE.md
Requires-Dist: ovos-workshop>=0.0.7,~=0.0
Requires-Dist: beautifulsoup4~=4.11
Requires-Dist: neon-utils~=1.12
Requires-Dist: ovos-utils~=0.1
Provides-Extra: test
Requires-Dist: neon-minerva[padatious]~=0.3; extra == "test"
